flarch/__about__.py
flarch/__init__.py
flarch/cli.py
flarch/commands/format_drive.py
flarch/commands/nullify_drive.py
flarch/commands/write_image.py
flarch/utils/__init__.py
flarch/utils/commands_exist.py
flarch/utils/size_of_drive.py
flarch-0.3.1.dist-info/METADATA
flarch-0.3.1.dist-info/WHEEL
flarch-0.3.1.dist-info/entry_points.txt
flarch-0.3.1.dist-info/licenses/LICENSE.txt
flarch-0.3.1.dist-info/RECORD
