Metadata-Version: 2.3
Name: flarch
Version: 0.3.1
Summary: Write, read and format floppies with ease
Project-URL: Documentation, https://github.com/alex-rusakevich/flarch#readme
Project-URL: Issues, https://github.com/alex-rusakevich/flarch/issues
Project-URL: Source, https://github.com/alex-rusakevich/flarch
Author-email: Alexander Rusakevich <mr.alexander.rusakevich@gmail.com>
License-Expression: MIT
License-File: LICENSE.txt
Classifier: Development Status :: 4 - Beta
Classifier: Programming Language :: Python
Classifier: Programming Language :: Python :: 3.8
Classifier: Programming Language :: Python :: 3.9
Classifier: Programming Language :: Python :: 3.10
Classifier: Programming Language :: Python :: 3.11
Classifier: Programming Language :: Python :: 3.12
Classifier: Programming Language :: Python :: Implementation :: CPython
Classifier: Programming Language :: Python :: Implementation :: PyPy
Requires-Python: >=3.8
